bibble/__init__.py
bibble/_interface.py
bibble/library.py
bibble/model.py
bibble/py.typed
bibble/_templates/__init__.py
bibble/_templates/entry.bib.jinja
bibble/_templates/footer.bib.jinja
bibble/_templates/header.bib.jinja
bibble/_templates/lib.bib.jinja
bibble/bidi/__init__.py
bibble/bidi/braces.py
bibble/bidi/isbn.py
bibble/bidi/latex.py
bibble/bidi/names.py
bibble/bidi/paths.py
bibble/bidi/tags.py
bibble/failure/__init__.py
bibble/failure/_interface.py
bibble/failure/duplicate_handler.py
bibble/failure/failure_handler.py
bibble/fields/__init__.py
bibble/fields/_interface.py
bibble/fields/field_accumulator.py
bibble/fields/field_sorter.py
bibble/fields/field_substitutor.py
bibble/fields/title_reader.py
bibble/fields/url_reader.py
bibble/files/__init__.py
bibble/files/_firefox.py
bibble/files/_interface.py
bibble/files/online.py
bibble/files/path_reader.py
bibble/files/path_writer.py
bibble/io/__init__.py
bibble/io/_interface.py
bibble/io/_util.py
bibble/io/jinja_writer.py
bibble/io/reader.py
bibble/io/writer.py
bibble/latex/__init__.py
bibble/latex/_interface.py
bibble/latex/_util.py
bibble/latex/reader.py
bibble/latex/writer.py
bibble/metadata/__init__.py
bibble/metadata/_interface.py
bibble/metadata/data_insert.py
bibble/metadata/entry_sorter.py
bibble/metadata/isbn_validator.py
bibble/metadata/isbn_writer.py
bibble/metadata/key_locker.py
bibble/metadata/metadata_writer.py
bibble/metadata/tags_reader.py
bibble/metadata/tags_writer.py
bibble/people/__init__.py
bibble/people/_interface.py
bibble/people/name_reader.py
bibble/people/name_sub.py
bibble/people/name_writer.py
bibble/reporters/__init__.py
bibble/reporters/summary.py
bibble/util/__init__.py
bibble/util/middlecore.py
bibble/util/mixins.py
bibble/util/name_parts.py
bibble/util/pair_stack.py
bibble/util/selectors.py
bibble/util/str_transform_m.py
bibtex_bibble-0.4.0.dist-info/METADATA
bibtex_bibble-0.4.0.dist-info/WHEEL
bibtex_bibble-0.4.0.dist-info/licenses/LICENSE
bibtex_bibble-0.4.0.dist-info/RECORD
