Metadata-Version: 2.4
Name: bibtex-bibble
Version: 0.4.0
Project-URL: homepage, https://jgrey4296.github.io/bibble
Project-URL: documentation, https://bibble.readthedocs.io/en/latest
Project-URL: repository, https://github.com/jgrey4296/bibble
Project-URL: changelog, https://github.com/bibble/blob/master/CHANGELOG.md
Author-email: John Grey <jgrey.n.plus.one@gmail.com>
License-File: LICENSE
Classifier: Programming Language :: Python
Requires-Python: >=3.12
Requires-Dist: bibtexparser>=2.0.0b8
Requires-Dist: internetarchive>=5.3.1
Requires-Dist: isbn-hyphenate>=1.0.4
Requires-Dist: jgdv>=1.0
Requires-Dist: jinja2>=3.1.6
Requires-Dist: jsonlines>=4.0.0
Requires-Dist: pyisbn>=1.3.1
Requires-Dist: selenium>=4.30.0
Requires-Dist: tqdm>=4.67.1
Requires-Dist: waybackpy>=3.0.6
